rsna/__init__.py
rsna/aug.py
rsna/dataloader.py
rsna/engine.py
rsna/nn.py
rsna/utils.py
rsna-0.0.1.dist-info/LICENSE
rsna-0.0.1.dist-info/METADATA
rsna-0.0.1.dist-info/WHEEL
rsna-0.0.1.dist-info/top_level.txt
rsna-0.0.1.dist-info/zip-safe
rsna-0.0.1.dist-info/RECORD
