Metadata-Version: 2.1
Name: rsna
Version: 0.0.1
Summary: Mini library for the RSNA-MICCAI Brain Tumor Radiogenomic Classification Kaggle Competition
Home-page: https://github.com/SauravMaheshkar/RSNA-MICCAI
Author: Saurav Maheshkar
Author-email: sauravvmaheshkar@gmail.com
License: MIT
Platform: UNKNOWN
License-File: LICENSE
